[[["af3f9ebb-2281-4a02-890e-38a0db42d0ac",{"pageContent":"Universitas Ciputra mempunyai 2 gedung, gedung pertama adalah gedung lama atau disebut UC main building dengan tinggi 7 lantai, sedangkan gedung kedua biasa disebut UC Tower dengan tinggi 24 lantai. Apple Developer Academy milik UC berada di UC Tower lantai 7.\r\n\r\nDisekitar gedung Universitas Ciputra terdapat 3 apartemen yaitu Denver, Berkeley, dan Cornell.","metadata":{"source":"/home/abuku/projects/ai/yucca-ai/backend/knowledge_base/kb.txt","loc":{"lines":{"from":1,"to":3}}}}]],{"0":"af3f9ebb-2281-4a02-890e-38a0db42d0ac"}]